wideryolo/predict.py
wideryolo-0.0.8.dist-info/LICENSE
wideryolo-0.0.8.dist-info/METADATA
wideryolo-0.0.8.dist-info/WHEEL
wideryolo-0.0.8.dist-info/top_level.txt
wideryolo-0.0.8.dist-info/RECORD
