Metadata-Version: 2.1
Name: wideryolo
Version: 0.0.8
Summary: Wider-Yolo Kütüphanesi ile Yüz Tespit Uygulamanı Yap
Home-page: https://github.com/kadirnar/
Author: Kadir Nar
Author-email: kadir.nar@hotmail.com
License: MIT
Platform: UNKNOWN
Classifier: License :: OSI Approved :: MIT License
Classifier: Programming Language :: Python :: 3
Classifier: Programming Language :: Python :: 3.6
Classifier: Programming Language :: Python :: 3.7
Classifier: Programming Language :: Python :: 3.8
Classifier: Programming Language :: Python :: 3.9
License-File: LICENSE
Requires-Dist: requirements.txt
